docp_core/__init__.py
docp_core/_version.py
docp_core/changelog.py
docp_core/utilities.py
docp_core/config/__init__.py
docp_core/config/config.py
docp_core/config/config.toml
docp_core/objects/__init__.py
docp_core/objects/documentobjects.py
docp_core/objects/textobject.py
docp_core-1.0.1.dist-info/licenses/LICENSE
docp_core-1.0.1.dist-info/METADATA
docp_core-1.0.1.dist-info/WHEEL
docp_core-1.0.1.dist-info/top_level.txt
docp_core-1.0.1.dist-info/RECORD
