Metadata-Version: 2.4
Name: docp-core
Version: 1.0.1
Summary: A basic document parsing utility. (Core)
Author-email: The Developers <development@s3dev.uk>
License-Expression: GPL-3.0-or-later
Project-URL: Documentation, https://docp-core.readthedocs.io
Project-URL: Homepage, https://github.com/s3dev/docp-core
Project-URL: Repository, https://github.com/s3dev/docp-core
Keywords: document,library,parsing,utility,utilities
Classifier: Development Status :: 5 - Production/Stable
Classifier: Intended Audience :: Developers
Classifier: Intended Audience :: End Users/Desktop
Classifier: Programming Language :: Python :: 3.11
Classifier: Programming Language :: Python :: 3.12
Classifier: Programming Language :: Python :: 3.13
Classifier: Programming Language :: Python :: 3.14
Classifier: Programming Language :: Python :: Implementation :: CPython
Classifier: Operating System :: POSIX :: Linux
Classifier: Operating System :: Microsoft :: Windows
Classifier: Topic :: Software Development
Classifier: Topic :: Software Development :: Libraries
Classifier: Topic :: Utilities
Requires-Python: >=3.11
License-File: LICENSE
Requires-Dist: utils4>=1.8.0
Dynamic: license-file
